{
  "kind": "singleType",
  "collectionName": "regulatory_documents_pages",
  "info": {
    "singularName": "regulatory-documents-page",
    "pluralName": "regulatory-documents-pages",
    "displayName": "RegulatoryDocumentsPage"
  },
  "options": {
    "draftAndPublish": true
  },
  "attributes": {
    "license": {
      "allowedTypes": [
        "images"
      ],
      "type": "media",
      "multiple": true
    },
    "regulatory_documents_google_drive_folderID": {
      "type": "string"
    }
  }
}
